README.md
setup.py
blum_crypto/__init__.py
blum_crypto/config.py
blum_crypto/gui.py
blum_crypto/main.py
blum_crypto.egg-info/PKG-INFO
blum_crypto.egg-info/SOURCES.txt
blum_crypto.egg-info/dependency_links.txt
blum_crypto.egg-info/entry_points.txt
blum_crypto.egg-info/requires.txt
blum_crypto.egg-info/top_level.txt