Metadata-Version: 2.1
Name: blum_crypto
Version: 0.1
Summary: A clicker application for specific images
Requires-Dist: opencv-python
Requires-Dist: pillow
Requires-Dist: pyautogui
Requires-Dist: keyboard
